ulid_dates/__init__.py
ulid_dates/core.py
ulid_dates-0.2.0.dist-info/licenses/LICENSE
ulid_dates-0.2.0.dist-info/METADATA
ulid_dates-0.2.0.dist-info/WHEEL
ulid_dates-0.2.0.dist-info/top_level.txt
ulid_dates-0.2.0.dist-info/RECORD
