Metadata-Version: 2.4
Name: ulid-dates
Version: 0.2.0
Summary: Determine ULID prefixes for date ranges
Author-email: Rodney Haywood <rodos@haywood.org>
License-Expression: MIT
Project-URL: Homepage, https://github.com/Iamrodos/ulid-dates
Project-URL: Issues, https://github.com/Iamrodos/ulid-dates/issues
Classifier: Programming Language :: Python :: 3
Classifier: Operating System :: OS Independent
Requires-Python: >=3.13
License-File: LICENSE
Requires-Dist: py-ulid>=1.0.3
Dynamic: license-file
